nearai_langchain/__init__.py
nearai_langchain/agent_data.py
nearai_langchain/constants.py
nearai_langchain/local_config.py
nearai_langchain/local_environment.py
nearai_langchain/local_nearai_chat_model.py
nearai_langchain/orchestrator.py
nearai_langchain/remote_nearai_chat_model.py
nearai_langchain/secure_openai_clients.py
nearai_langchain-0.0.13.dist-info/LICENSE
nearai_langchain-0.0.13.dist-info/METADATA
nearai_langchain-0.0.13.dist-info/WHEEL
nearai_langchain-0.0.13.dist-info/RECORD
