Metadata-Version: 2.3
Name: nearai-langchain
Version: 0.0.13
Summary: NearAI LangChain Integration
Author: Support
Author-email: support@near.ai
Requires-Python: >=3.10,<3.12
Classifier: Programming Language :: Python :: 3
Classifier: Programming Language :: Python :: 3.10
Classifier: Programming Language :: Python :: 3.11
Requires-Dist: coinbase-agentkit (>=0.4.0)
Requires-Dist: coinbase-agentkit-langchain (>=0.3.0)
Requires-Dist: langchain (>=0.3.4,<0.4.0)
Requires-Dist: langchain-fireworks (>=0.2.6,<0.3.0)
Requires-Dist: langchain-openai (>=0.3.6,<0.4.0)
Requires-Dist: langgraph (>=0.2.74,<0.3.0)
Requires-Dist: nearai (>=0.1.13,<0.2.0)
Requires-Dist: pydantic (>=2.7.1,<=2.10.6)
Project-URL: Repository, https://github.com/nearai/nearai_langchain
